dcm/__init__.py
dcm/dcm.py
dcm/fast_mst.py
dcm/log.py
dcm/logger.py
dcm/mst.py
examples/__init__.py
examples/creditcard_C12.py
examples/creditcard_F1.py
examples/creditcard_N1.py
examples/datasets.py
data_complexity-0.1.3.dist-info/LICENSE
data_complexity-0.1.3.dist-info/METADATA
data_complexity-0.1.3.dist-info/WHEEL
data_complexity-0.1.3.dist-info/top_level.txt
data_complexity-0.1.3.dist-info/RECORD
