Metadata-Version: 2.1
Name: data-complexity
Version: 0.1.3
Summary: Data Complexity Measures
Home-page: https://github.com/ngocson2vn/data-complexity
Author: Son Nguyen
Author-email: ngocson2vn@gmail.com
License: MIT
Platform: UNKNOWN
Classifier: Programming Language :: Python :: 3
Classifier: License :: OSI Approved :: MIT License
Classifier: Operating System :: OS Independent
Requires-Python: >=3.6
Requires-Dist: numpy
Requires-Dist: gower
